shared_nearest_neighbors/__init__.py
shared_nearest_neighbors/shared_nearest_neighbors.py
shared_nearest_neighbors-0.1.0.dist-info/AUTHORS.rst
shared_nearest_neighbors-0.1.0.dist-info/LICENSE
shared_nearest_neighbors-0.1.0.dist-info/METADATA
shared_nearest_neighbors-0.1.0.dist-info/WHEEL
shared_nearest_neighbors-0.1.0.dist-info/top_level.txt
shared_nearest_neighbors-0.1.0.dist-info/RECORD
