Metadata-Version: 2.1
Name: shared-nearest-neighbors
Version: 0.1.0
Summary: SNN Algorithm
Home-page: https://github.com/felipeangelimvieira/shared_nearest_neighbors
Author: Felipe L Angelim Vieira
Author-email: felipeangelim@gmail.com
License: MIT license
Keywords: shared_nearest_neighbors
Platform: UNKNOWN
Classifier: Development Status :: 2 - Pre-Alpha
Classifier: Intended Audience :: Developers
Classifier: License :: OSI Approved :: MIT License
Classifier: Natural Language :: English
Classifier: Programming Language :: Python :: 3
Classifier: Programming Language :: Python :: 3.6
Classifier: Programming Language :: Python :: 3.7
Classifier: Programming Language :: Python :: 3.8
Requires-Python: >=3.6
Requires-Dist: sklearn (>=0.20.0)
Requires-Dist: numpy (>=1.18.0)
